README.md
setup.py
cli/__init__.py
cli/main.py
mohcli.egg-info/PKG-INFO
mohcli.egg-info/SOURCES.txt
mohcli.egg-info/dependency_links.txt
mohcli.egg-info/entry_points.txt
mohcli.egg-info/requires.txt
mohcli.egg-info/top_level.txt