Metadata-Version: 2.1
Name: mohcli
Version: 0.0.0
Summary: A CLI tool for generating a bare-bone FastAPI project
Home-page: https://github.com/kenmoh/moh_cli
Author: Ken Aremoh
Author-email: Kenneth.aremoh@gmail.com
Classifier: Programming Language :: Python :: 3
Classifier: License :: OSI Approved :: MIT License
Classifier: Operating System :: OS Independent
Requires-Python: >=3.6
